typethon/__init__.py
typethon/__version__.py
typethon/build_metadata.json
typethon/cli.py
typethon/decorators.py
typethon/utils/__init__.py
typethon/utils/cli_arg_validators.py
typethon/utils/type_checkers.py
typethon-0.0.2.dist-info/LICENSE
typethon-0.0.2.dist-info/METADATA
typethon-0.0.2.dist-info/WHEEL
typethon-0.0.2.dist-info/entry_points.txt
typethon-0.0.2.dist-info/top_level.txt
typethon-0.0.2.dist-info/RECORD
