Metadata-Version: 2.1
Name: typethon
Version: 0.0.2
Summary: Typethon is an extremely lightweight and simple module for strongly typed Python.
Home-page: https://github.com/obfuscatedgenerated/typethon
Author: obfuscatedgenerated
Author-email: pip@obfuscatedgenerated.ml
License: MIT
Keywords: type,check,decorators,cli,lint,lightweight
Platform: UNKNOWN
Classifier: Development Status :: 3 - Alpha
Classifier: Intended Audience :: Developers
Classifier: Topic :: Software Development :: Libraries :: Python Modules
Classifier: Topic :: Software Development :: Bug Tracking
Classifier: Topic :: Software Development :: Testing
Classifier: Topic :: Software Development :: Quality Assurance
Classifier: Topic :: Games/Entertainment
Classifier: License :: OSI Approved :: MIT License
Classifier: Programming Language :: Python :: 3
Classifier: Programming Language :: Python :: 3.4
Classifier: Programming Language :: Python :: 3.5
Classifier: Programming Language :: Python :: 3.6
Classifier: Programming Language :: Python :: 3.7
Classifier: Programming Language :: Python :: 3.8
Classifier: Programming Language :: Python :: 3.9
